Metadata-Version: 1.0
Name: gs-bn-probdist
Version: 1.1
Summary: Gaussian distributions
Home-page: UNKNOWN
Author: Himanshu Singh Sikarwar
Author-email: himanshusingh3639@gmail.com
License: UNKNOWN
Platform: UNKNOWN
